[
  {
    "id": "bb1",
    "season": "Big Brother 1",
    "image": "images/seasons/1.png",
    "format": "original",
    "jury-size": 0,
    "finale-size": 3
  },
  {
    "id": "bb2",
    "season": "Big Brother 2",
    "image": "images/seasons/2.png",
    "format": "revised",
    "jury-size": 9,
    "finale-size": 2
  },
  {
    "id": "bb3",
    "season": "Big Brother 3",
    "image": "images/seasons/3.png",
    "format": "regular",
    "jury-size": 10
  },
  {
    "id": "bb4",
    "season": "Big Brother 4",
    "image": "images/seasons/4.png",
    "format": "regular"
  },
  {
    "id": "bb5",
    "season": "Big Brother 5",
    "image": "images/seasons/5.png"
  },
  {
    "id": "bb6",
    "season": "Big Brother 6",
    "image": "images/seasons/6.png"
  },
  {
    "id": "bb7",
    "season": "Big Brother 7",
    "image": "images/seasons/7.png"
  },
  {
    "id": "bb8",
    "season": "Big Brother 8",
    "image": "images/seasons/8.png"
  },
  {
    "id": "bb9",
    "season": "Big Brother 9",
    "image": "images/seasons/9.png"
  },
  {
    "id": "bb10",
    "season": "Big Brother 10",
    "image": "images/seasons/10.png"
  },
  {
    "id": "bb11",
    "season": "Big Brother 11",
    "image": "images/seasons/11.png"
  },
  {
    "id": "bb12",
    "season": "Big Brother 12",
    "image": "images/seasons/12.png"
  },
  {
    "id": "bb13",
    "season": "Big Brother 13",
    "image": "images/seasons/13.png"
  },
  {
    "id": "bb14",
    "season": "Big Brother 14",
    "image": "images/seasons/14.png"
  },
  {
    "id": "bb15",
    "season": "Big Brother 15",
    "image": "images/seasons/15.png"
  },
  {
    "id": "bb16",
    "season": "Big Brother 16",
    "image": "images/seasons/16.png"
  },
  {
    "id": "bb17",
    "season": "Big Brother 17",
    "image": "images/seasons/17.png"
  },
  {
    "id": "bb18",
    "season": "Big Brother 18",
    "image": "images/seasons/18.png"
  },
  {
    "id": "bb19",
    "season": "Big Brother 19",
    "image": "images/seasons/19.png"
  },
  {
    "id": "bb20",
    "season": "Big Brother 20",
    "image": "images/seasons/20.png"
  },
  {
    "id": "bb21",
    "season": "Big Brother 21",
    "image": "images/seasons/21.png"
  },
  {
    "id": "bb22",
    "season": "Big Brother 22",
    "image": "images/seasons/22.png"
  },
  {
    "id": "bb23",
    "season": "Big Brother 23",
    "image": "images/seasons/23.png"
  },
  {
    "id": "bb24",
    "season": "Big Brother 24",
    "image": "images/seasons/24.png"
  },
  {
    "id": "bb25",
    "season": "Big Brother 25",
    "image": "images/seasons/25.png"
  },
  {
    "id": "bb26",
    "season": "Big Brother 26",
    "image": "images/seasons/26.png"
  },
  {
    "id": "bb27",
    "season": "Big Brother 27",
    "image": "images/seasons/27.png",
    "format": "regular",
    "jury-size": 7,
    "finale-size": 2
  }
]